<?xml version="1.0" encoding="UTF-8"?>
<database>
    <element attributes="live_feed=true" label="Employee Provident Fund" max_length="40" name="x_11409_employee_p_employee_provident_fund" type="collection">
        <element attributes="edge_encryption_enabled=true" label="Current Account No" max_length="40" name="current_account_no" type="string"/>
        <element attributes="edge_encryption_enabled=true" choice="1" label="Employer" max_length="40" name="employer" type="string">
            <choice>
                <element label="HCL Tech" sequence="0" value="HCL Tech"/>
                <element label="Unisys Technology" sequence="1" value="Unisys Technology"/>
                <element label="Thomson Reuters" sequence="2" value="Thomson Reuters"/>
            </choice>
        </element>
        <element attributes="edge_encryption_enabled=true" label="Member Name" max_length="40" name="member_name" type="string"/>
        <element default="javascript:global.getNextObjNumberPadded();" label="Number" max_length="40" name="number" type="string"/>
        <element attributes="edge_encryption_enabled=true" label="Previous Account No" max_length="40" name="previous_account_no" type="string"/>
        <element attributes="edge_encryption_enabled=true" choice="1" label="Status of Claim" max_length="40" name="status_of_claim" type="string">
            <choice>
                <element label="Completed" sequence="0" value="Completed"/>
                <element label="Pending" sequence="1" value="Pending"/>
                <element label="InProgress" sequence="2" value="InProgress"/>
                <element label="Rejected" sequence="3" value="Rejected"/>
            </choice>
        </element>
        <element default="javascript:current.getTableName();" dynamic_default_value="b5cb83a85f220100a9ad2572f2b4773c" label="Class" max_length="80" name="sys_class_name" type="sys_class_name" use_dynamic_default="true"/>
        <element attributes="edge_encryption_enabled=true" label="UAN No" max_length="40" name="uan_no" type="string"/>
    </element>
</database>
